rclone_python/__init__.py
rclone_python/hash_types.py
rclone_python/rclone.py
rclone_python/remote_types.py
rclone_python/utils.py
rclone_python_lp_asset-0.1.13.dist-info/LICENSE
rclone_python_lp_asset-0.1.13.dist-info/METADATA
rclone_python_lp_asset-0.1.13.dist-info/WHEEL
rclone_python_lp_asset-0.1.13.dist-info/top_level.txt
rclone_python_lp_asset-0.1.13.dist-info/RECORD
