Metadata-Version: 2.1
Name: rclone-python-lp-asset
Version: 0.1.13
Summary: A python wrapper for rclone.
Home-page: https://github.com/ligeng8848/rclone_python
Author: Johannes Gundlach
Keywords: rclone,wrapper,cloud sync
Classifier: Programming Language :: Python :: 3
Classifier: License :: OSI Approved :: MIT License
Classifier: Operating System :: OS Independent
Requires-Python: >=3.6
License-File: LICENSE
Requires-Dist: rich
